test/test_tkmacosx/__init__.py
test/test_tkmacosx/test_variables.py
test/test_tkmacosx/test_widgets.py
tkmacosx/__init__.py
tkmacosx/__main__.py
tkmacosx/basewidgets/__init__.py
tkmacosx/basewidgets/button_base.py
tkmacosx/basewidgets/colorscale_base.py
tkmacosx/basewidgets/marquee_base.py
tkmacosx/basewidgets/radiobutton_base.py
tkmacosx/basewidgets/sframe_base.py
tkmacosx/utils/__init__.py
tkmacosx/utils/check_parameter.py
tkmacosx/utils/colorvar_patches.py
tkmacosx/variables/__init__.py
tkmacosx/variables/colorvar.py
tkmacosx/variables/dictvar.py
tkmacosx/variables/savevar.py
tkmacosx/widgets/__init__.py
tkmacosx/widgets/button.py
tkmacosx/widgets/circlebutton.py
tkmacosx/widgets/colorscale.py
tkmacosx/widgets/marquee.py
tkmacosx/widgets/radiobutton.py
tkmacosx/widgets/sframe.py
tkmacosx-1.0.5.dist-info/LICENSE
tkmacosx-1.0.5.dist-info/METADATA
tkmacosx-1.0.5.dist-info/WHEEL
tkmacosx-1.0.5.dist-info/top_level.txt
tkmacosx-1.0.5.dist-info/RECORD
