Metadata-Version: 2.1
Name: tkmacosx
Version: 1.0.5
Summary: Tkmacosx is a Python library extension to the Tkinter module that let you change background color of the button on macOS.
Home-page: https://github.com/Saadmairaj/tkmacosx
Author: Saad Mairaj
Author-email: Saadmairaj@yahoo.in
License: Apache
Project-URL: Bug Reports, https://github.com/Saadmairaj/tkmacosx/issues
Project-URL: Source, https://github.com/Saadmairaj/tkmacosx
Project-URL: Documentation, https://github.com/Saadmairaj/tkmacosx#documentation
Keywords: tkinter,macos,variable,widgets,colorscale,tk,color,button,circlebutton,marquee,tkinter-widgets,tkinter-scrollableframe,scrollableframe
Platform: UNKNOWN
Classifier: Development Status :: 6 - Mature
Classifier: Environment :: MacOS X
Classifier: Environment :: Win32 (MS Windows)
Classifier: Environment :: X11 Applications
Classifier: Intended Audience :: Developers
Classifier: Intended Audience :: Education
Classifier: Intended Audience :: End Users/Desktop
Classifier: Operating System :: OS Independent
Classifier: Programming Language :: Python :: 3 :: Only
Classifier: Programming Language :: Python :: 3.0
Classifier: Programming Language :: Python :: 3.1
Classifier: Programming Language :: Python :: 3.2
Classifier: Programming Language :: Python :: 3.3
Classifier: Programming Language :: Python :: 3.4
Classifier: Programming Language :: Python :: 3.5
Classifier: Programming Language :: Python :: 3.6
Classifier: Programming Language :: Python :: 3.7
Classifier: Programming Language :: Python :: 3.8
Classifier: Programming Language :: Python :: 3.9
Classifier: Topic :: Software Development
Classifier: Topic :: Software Development :: Build Tools
Classifier: Topic :: Software Development :: Libraries :: Python Modules
Classifier: Topic :: Software Development :: Widget Sets
Classifier: License :: OSI Approved :: Apache Software License
Requires-Python: >=3
License-File: LICENSE
